dbml_builder/__init__.py
dbml_builder/build.py
dbml_builder/cli.py
dbml_builder/fix.py
dbml_builder-0.4.1.dist-info/LICENSE
dbml_builder-0.4.1.dist-info/METADATA
dbml_builder-0.4.1.dist-info/WHEEL
dbml_builder-0.4.1.dist-info/entry_points.txt
dbml_builder-0.4.1.dist-info/RECORD
